wi_fipasswordgenerator/__init__.py
wi_fipasswordgenerator/core.py
wi_fipasswordgenerator/icon.png
wi_fipasswordgenerator/requirements-dev.txt
wi_fipasswordgenerator/wpg.py
wi_fipasswordgenerator-0.3.85.dist-info/METADATA
wi_fipasswordgenerator-0.3.85.dist-info/WHEEL
wi_fipasswordgenerator-0.3.85.dist-info/entry_points.txt
wi_fipasswordgenerator-0.3.85.dist-info/licenses/LICENSE
wi_fipasswordgenerator-0.3.85.dist-info/RECORD
