Metadata-Version: 2.4
Name: Wi-FiPasswordGenerator
Version: 0.3.85
Summary: A lightweight password generator that creates strong passwords up to 63 characters.
Project-URL: Homepage, https://github.com/heit0r/Wi-FiPasswordGenerator
Project-URL: Issues, https://github.com/heit0r/Wi-FiPasswordGenerator/issues
Author-email: heit0r <heitordrp@gmail.com>
License: MIT License
License-File: LICENSE
Classifier: Intended Audience :: End Users/Desktop
Classifier: Operating System :: OS Independent
Classifier: Topic :: Education :: Testing
Classifier: Topic :: Security
Classifier: Topic :: Security :: Cryptography
Requires-Python: >=3.9
Requires-Dist: customtkinter
Requires-Dist: qrcode[pil]
Provides-Extra: dev
Requires-Dist: pytest; extra == 'dev'
Requires-Dist: pytest-cov; extra == 'dev'
